Workbook

Sheet Trade Register
A1: Trade ID | B1: Client | C1: Security | D1: Asset Type | E1: Buy/Sell | F1: Quantity | G1: Price | H1: Trade Date | I1: Settlement Date | J1: Currency
A2: TR001 | B2: Alpha Capital | C2: AAPL | D2: Equity | E2: Buy | F2: 500 | G2: 225 | H2: 46266 | I2: 46268 | J2: USD
A3: TR002 | B3: Beta Investments | C3: MSFT | D3: Equity | E3: Sell | F3: 300 | G3: 505 | H3: 46266 | I3: 46268 | J3: USD
A4: TR003 | B4: Gamma Fund | C4: TSLA | D4: Equity | E4: Buy | F4: 400 | G4: 345 | H4: 46266 | I4: 46268 | J4: USD
A5: TR004 | B5: Delta Asset Mgmt | C5: AMZN | D5: Equity | E5: Buy | F5: 250 | G5: 235 | H5: 46267 | I5: 46269 | J5: USD
A6: TR005 | B6: Alpha Capital | C6: GOOGL | D6: Equity | E6: Sell | F6: 350 | G6: 210 | H6: 46267 | I6: 46269 | J6: USD
A7: TR006 | B7: Beta Investments | C7: JPM | D7: Equity | E7: Buy | F7: 600 | G7: 295 | H7: 46267 | I7: 46269 | J7: USD
A8: TR007 | B8: Gamma Fund | C8: RELIANCE | D8: Equity | E8: Buy | F8: 800 | G8: 1410 | H8: 46268 | I8: 46272 | J8: INR
A9: TR008 | B9: Delta Asset Mgmt | C9: TCS | D9: Equity | E9: Sell | F9: 500 | G9: 3020 | H9: 46268 | I9: 46272 | J9: INR
A10: TR009 | B10: Alpha Capital | C10: HDFCBANK | D10: Equity | E10: Buy | F10: 700 | G10: 1980 | H10: 46268 | I10: 46272 | J10: INR
A11: TR010 | B11: Beta Investments | C11: INFY | D11: Equity | E11: Sell | F11: 900 | G11: 1520 | H11: 46269 | I11: 46273 | J11: INR
A12: TR011 | B12: Gamma Fund | C12: US10Y | D12: Bond | E12: Buy | F12: 100 | G12: 98.5 | H12: 46269 | I12: 46273 | J12: USD
A13: TR012 | B13: Delta Asset Mgmt | C13: UK GILT | D13: Bond | E13: Sell | F13: 150 | G13: 101.25 | H13: 46269 | I13: 46273 | J13: GBP
... A21: TR020 | B21: Delta Asset Mgmt | C21: HINDUNILVR | D21: Equity | E21: Sell | F21: 400 | G21: 2450 | H21: 46271 | I21: 46273 | J21: INR

Sheet Counterparty Trades
A1: Trade ID | B1: Client | C1: Security | D1: Asset Type | E1: Buy/Sell | F1: Quantity | G1: Price | H1: Trade Date | I1: Settlement Date | J1: Currency
A2: TR001 | B2: Alpha Capital | C2: AAPL | D2: Equity | E2: Buy | F2: 500 | G2: 225 | H2: 46266 | I2: 46268 | J2: USD
A3: TR002 | B3: Beta Investments | C3: MSFT | D3: Equity | E3: Sell | F3: 300 | G3: 505 | H3: 46266 | I3: 46268 | J3: USD
A4: TR003 | B4: Gamma Fund | C4: TSLA | D4: Equity | E4: Buy | F4: 400 | G4: 345 | H4: 46266 | I4: 46268 | J4: USD
A5: TR004 | B5: Delta Asset Mgmt | C5: AMZN | D5: Equity | E5: Buy | F5: 250 | G5: 235 | H5: 46267 | I5: 46269 | J5: USD
A6: TR005 | B6: Alpha Capital | C6: GOOGL | D6: Equity | E6: Sell | F6: 350 | G6: 211 | H6: 46267 | I6: 46269 | J6: USD
A7: TR006 | B7: Beta Investments | C7: JPM | D7: Equity | E7: Buy | F7: 650 | G7: 295 | H7: 46267 | I7: 46269 | J7: USD
A8: TR007 | B8: Gamma Fund | C8: RELIANCE | D8: Equity | E8: Buy | F8: 800 | G8: 1410 | H8: 46268 | I8: 46272 | J8: INR
A9: TR008 | B9: Delta Asset Mgmt | C9: TCS | D9: Equity | E9: Sell | F9: 500 | G9: 3020 | H9: 46269 | I9: 46272 | J9: INR
A10: TR009 | B10: Alpha Capital | C10: HDFCBANK | D10: Equity | E10: Buy | F10: 700 | G10: 1980 | H10: 46268 | I10: 46273 | J10: INR
A11: TR010 | B11: Beta Investments | C11: INFY | D11: Equity | E11: Buy | F11: 900 | G11: 1520 | H11: 46269 | I11: 46273 | J11: INR
A12: TR011 | B12: Gamma Fund | C12: US10Y | D12: Bond | E12: Buy | F12: 100 | G12: 98.5 | H12: 46269 | I12: 46273 | J12: USD
A13: TR012 | B13: Delta Asset Mgmt | C13: UK GILT | D13: Bond | E13: Sell | F13: 150 | G13: 101.25 | H13: 46269 | I13: 46273 | J13: GBP
... A21: TR020 | B21: Delta Asset Mgmt | C21: HINDUNILVR | D21: Equity | E21: Sell | F21: 400 | G21: 2450 | H21: 46271 | I21: 46273 | J21: INR

Sheet Trade Matching
A1: Trade ID | B1: Internal Quantity | C1: Counterparty Quantity | D1: Internal Price | E1: Counterparty Price | F1: Quantity Match | G1: Price Match | H1: Internal Trade Date | I1: Counterparty Trade Date | J1: Trade Date Match | K1: Internal Settlement Date | L1: Counterparty Settlement Date | M1: Settlement Date Match | N1: Internal Buy/Sell | O1: Counterparty Buy/Sell | P1: Buy/Sell Match
A2: TR001 | B2: =_xlfn.XLOOKUP(A2,'Trade Register'!A:A,'Trade Register'!F:F,"Not Found") -> 500 | C2: =_xlfn.XLOOKUP(A2,'Counterparty Trades'!A:A,'Counterparty Trades'!F:F,"Not Found") -> 500 | D2: =_xlfn.XLOOKUP(A2,'Trade Register'!A:A,'Trade Register'!G:G,"Not Found") -> 225 | E2: =_xlfn.XLOOKUP(A2,'Counterparty Trades'!A:A,'Counterparty Trades'!G:G,"Not Found") -> 225 | F2: =IF(B2=C2,"Match","Break") -> Match | G2: =IF(D2=E2,"Match","Break") -> Match | H2: =_xlfn.XLOOKUP(A2,'Trade Register'!A:A,'Trade Register'!H:H,"Not Found") -> 46266 | I2: =_xlfn.XLOOKUP(A2,'Counterparty Trades'!A:A,'Counterparty Trades'!H:H,"Not Found") -> 46266 | J2: =IF(H2=I2,"Match","Break") -> Match | K2: =_xlfn.XLOOKUP(A2,'Trade Register'!A:A,'Trade Register'!I:I,"Not Found") -> 46268 | L2: =_xlfn.XLOOKUP(A2,'Counterparty Trades'!A:A,'Counterparty Trades'!I:I,"Not Found") -> 46268 | M2: =IF(K2=L2,"Match","Break") -> Match | N2: =_xlfn.XLOOKUP(A2,'Trade Register'!A:A,'Trade Register'!E:E,"Not Found") -> Buy | O2: =_xlfn.XLOOKUP(A2,'Counterparty Trades'!A:A,'Counterparty Trades'!E:E,"Not Found") -> Buy | P2: =IF(N2=O2,"Match","Break") -> Match
A3: TR002 | B3: =_xlfn.XLOOKUP(A3,'Trade Register'!A:A,'Trade Register'!F:F,"Not Found") -> 300 | C3: =_xlfn.XLOOKUP(A3,'Counterparty Trades'!A:A,'Counterparty Trades'!F:F,"Not Found") -> 300 | D3: =_xlfn.XLOOKUP(A3,'Trade Register'!A:A,'Trade Register'!G:G,"Not Found") -> 505 | E3: =_xlfn.XLOOKUP(A3,'Counterparty Trades'!A:A,'Counterparty Trades'!G:G,"Not Found") -> 505 | F3: =IF(B3=C3,"Match","Break") -> Match | G3: =IF(D3=E3,"Match","Break") -> Match | H3: =_xlfn.XLOOKUP(A3,'Trade Register'!A:A,'Trade Register'!H:H,"Not Found") -> 46266 | I3: =_xlfn.XLOOKUP(A3,'Counterparty Trades'!A:A,'Counterparty Trades'!H:H,"Not Found") -> 46266 | J3: =IF(H3=I3,"Match","Break") -> Match | K3: =_xlfn.XLOOKUP(A3,'Trade Register'!A:A,'Trade Register'!I:I,"Not Found") -> 46268 | L3: =_xlfn.XLOOKUP(A3,'Counterparty Trades'!A:A,'Counterparty Trades'!I:I,"Not Found") -> 46268 | M3: =IF(K3=L3,"Match","Break") -> Match | N3: =_xlfn.XLOOKUP(A3,'Trade Register'!A:A,'Trade Register'!E:E,"Not Found") -> Sell | O3: =_xlfn.XLOOKUP(A3,'Counterparty Trades'!A:A,'Counterparty Trades'!E:E,"Not Found") -> Sell | P3: =IF(N3=O3,"Match","Break") -> Match
A4: TR003 | B4: =_xlfn.XLOOKUP(A4,'Trade Register'!A:A,'Trade Register'!F:F,"Not Found") -> 400 | C4: =_xlfn.XLOOKUP(A4,'Counterparty Trades'!A:A,'Counterparty Trades'!F:F,"Not Found") -> 400 | D4: =_xlfn.XLOOKUP(A4,'Trade Register'!A:A,'Trade Register'!G:G,"Not Found") -> 345 | E4: =_xlfn.XLOOKUP(A4,'Counterparty Trades'!A:A,'Counterparty Trades'!G:G,"Not Found") -> 345 | F4: =IF(B4=C4,"Match","Break") -> Match | G4: =IF(D4=E4,"Match","Break") -> Match | H4: =_xlfn.XLOOKUP(A4,'Trade Register'!A:A,'Trade Register'!H:H,"Not Found") -> 46266 | I4: =_xlfn.XLOOKUP(A4,'Counterparty Trades'!A:A,'Counterparty Trades'!H:H,"Not Found") -> 46266 | J4: =IF(H4=I4,"Match","Break") -> Match | K4: =_xlfn.XLOOKUP(A4,'Trade Register'!A:A,'Trade Register'!I:I,"Not Found") -> 46268 | L4: =_xlfn.XLOOKUP(A4,'Counterparty Trades'!A:A,'Counterparty Trades'!I:I,"Not Found") -> 46268 | M4: =IF(K4=L4,"Match","Break") -> Match | N4: =_xlfn.XLOOKUP(A4,'Trade Register'!A:A,'Trade Register'!E:E,"Not Found") -> Buy | O4: =_xlfn.XLOOKUP(A4,'Counterparty Trades'!A:A,'Counterparty Trades'!E:E,"Not Found") -> Buy | P4: =IF(N4=O4,"Match","Break") -> Match
A5: TR004 | B5: =_xlfn.XLOOKUP(A5,'Trade Register'!A:A,'Trade Register'!F:F,"Not Found") -> 250 | C5: =_xlfn.XLOOKUP(A5,'Counterparty Trades'!A:A,'Counterparty Trades'!F:F,"Not Found") -> 250 | D5: =_xlfn.XLOOKUP(A5,'Trade Register'!A:A,'Trade Register'!G:G,"Not Found") -> 235 | E5: =_xlfn.XLOOKUP(A5,'Counterparty Trades'!A:A,'Counterparty Trades'!G:G,"Not Found") -> 235 | F5: =IF(B5=C5,"Match","Break") -> Match | G5: =IF(D5=E5,"Match","Break") -> Match | H5: =_xlfn.XLOOKUP(A5,'Trade Register'!A:A,'Trade Register'!H:H,"Not Found") -> 46267 | I5: =_xlfn.XLOOKUP(A5,'Counterparty Trades'!A:A,'Counterparty Trades'!H:H,"Not Found") -> 46267 | J5: =IF(H5=I5,"Match","Break") -> Match | K5: =_xlfn.XLOOKUP(A5,'Trade Register'!A:A,'Trade Register'!I:I,"Not Found") -> 46269 | L5: =_xlfn.XLOOKUP(A5,'Counterparty Trades'!A:A,'Counterparty Trades'!I:I,"Not Found") -> 46269 | M5: =IF(K5=L5,"Match","Break") -> Match | N5: =_xlfn.XLOOKUP(A5,'Trade Register'!A:A,'Trade Register'!E:E,"Not Found") -> Buy | O5: =_xlfn.XLOOKUP(A5,'Counterparty Trades'!A:A,'Counterparty Trades'!E:E,"Not Found") -> Buy | P5: =IF(N5=O5,"Match","Break") -> Match
A6: TR005 | B6: =_xlfn.XLOOKUP(A6,'Trade Register'!A:A,'Trade Register'!F:F,"Not Found") -> 350 | C6: =_xlfn.XLOOKUP(A6,'Counterparty Trades'!A:A,'Counterparty Trades'!F:F,"Not Found") -> 350 | D6: =_xlfn.XLOOKUP(A6,'Trade Register'!A:A,'Trade Register'!G:G,"Not Found") -> 210 | E6: =_xlfn.XLOOKUP(A6,'Counterparty Trades'!A:A,'Counterparty Trades'!G:G,"Not Found") -> 211 | F6: =IF(B6=C6,"Match","Break") -> Match | G6: =IF(D6=E6,"Match","Break") -> Break | H6: =_xlfn.XLOOKUP(A6,'Trade Register'!A:A,'Trade Register'!H:H,"Not Found") -> 46267 | I6: =_xlfn.XLOOKUP(A6,'Counterparty Trades'!A:A,'Counterparty Trades'!H:H,"Not Found") -> 46267 | J6: =IF(H6=I6,"Match","Break") -> Match | K6: =_xlfn.XLOOKUP(A6,'Trade Register'!A:A,'Trade Register'!I:I,"Not Found") -> 46269 | L6: =_xlfn.XLOOKUP(A6,'Counterparty Trades'!A:A,'Counterparty Trades'!I:I,"Not Found") -> 46269 | M6: =IF(K6=L6,"Match","Break") -> Match | N6: =_xlfn.XLOOKUP(A6,'Trade Register'!A:A,'Trade Register'!E:E,"Not Found") -> Sell | O6: =_xlfn.XLOOKUP(A6,'Counterparty Trades'!A:A,'Counterparty Trades'!E:E,"Not Found") -> Sell | P6: =IF(N6=O6,"Match","Break") -> Match
A7: TR006 | B7: =_xlfn.XLOOKUP(A7,'Trade Register'!A:A,'Trade Register'!F:F,"Not Found") -> 600 | C7: =_xlfn.XLOOKUP(A7,'Counterparty Trades'!A:A,'Counterparty Trades'!F:F,"Not Found") -> 650 | D7: =_xlfn.XLOOKUP(A7,'Trade Register'!A:A,'Trade Register'!G:G,"Not Found") -> 295 | E7: =_xlfn.XLOOKUP(A7,'Counterparty Trades'!A:A,'Counterparty Trades'!G:G,"Not Found") -> 295 | F7: =IF(B7=C7,"Match","Break") -> Break | G7: =IF(D7=E7,"Match","Break") -> Match | H7: =_xlfn.XLOOKUP(A7,'Trade Register'!A:A,'Trade Register'!H:H,"Not Found") -> 46267 | I7: =_xlfn.XLOOKUP(A7,'Counterparty Trades'!A:A,'Counterparty Trades'!H:H,"Not Found") -> 46267 | J7: =IF(H7=I7,"Match","Break") -> Match | K7: =_xlfn.XLOOKUP(A7,'Trade Register'!A:A,'Trade Register'!I:I,"Not Found") -> 46269 | L7: =_xlfn.XLOOKUP(A7,'Counterparty Trades'!A:A,'Counterparty Trades'!I:I,"Not Found") -> 46269 | M7: =IF(K7=L7,"Match","Break") -> Match | N7: =_xlfn.XLOOKUP(A7,'Trade Register'!A:A,'Trade Register'!E:E,"Not Found") -> Buy | O7: =_xlfn.XLOOKUP(A7,'Counterparty Trades'!A:A,'Counterparty Trades'!E:E,"Not Found") -> Buy | P7: =IF(N7=O7,"Match","Break") -> Match
A8: TR007 | B8: =_xlfn.XLOOKUP(A8,'Trade Register'!A:A,'Trade Register'!F:F,"Not Found") -> 800 | C8: =_xlfn.XLOOKUP(A8,'Counterparty Trades'!A:A,'Counterparty Trades'!F:F,"Not Found") -> 800 | D8: =_xlfn.XLOOKUP(A8,'Trade Register'!A:A,'Trade Register'!G:G,"Not Found") -> 1410 | E8: =_xlfn.XLOOKUP(A8,'Counterparty Trades'!A:A,'Counterparty Trades'!G:G,"Not Found") -> 1410 | F8: =IF(B8=C8,"Match","Break") -> Match | G8: =IF(D8=E8,"Match","Break") -> Match | H8: =_xlfn.XLOOKUP(A8,'Trade Register'!A:A,'Trade Register'!H:H,"Not Found") -> 46268 | I8: =_xlfn.XLOOKUP(A8,'Counterparty Trades'!A:A,'Counterparty Trades'!H:H,"Not Found") -> 46268 | J8: =IF(H8=I8,"Match","Break") -> Match | K8: =_xlfn.XLOOKUP(A8,'Trade Register'!A:A,'Trade Register'!I:I,"Not Found") -> 46272 | L8: =_xlfn.XLOOKUP(A8,'Counterparty Trades'!A:A,'Counterparty Trades'!I:I,"Not Found") -> 46272 | M8: =IF(K8=L8,"Match","Break") -> Match | N8: =_xlfn.XLOOKUP(A8,'Trade Register'!A:A,'Trade Register'!E:E,"Not Found") -> Buy | O8: =_xlfn.XLOOKUP(A8,'Counterparty Trades'!A:A,'Counterparty Trades'!E:E,"Not Found") -> Buy | P8: =IF(N8=O8,"Match","Break") -> Match
A9: TR008 | B9: =_xlfn.XLOOKUP(A9,'Trade Register'!A:A,'Trade Register'!F:F,"Not Found") -> 500 | C9: =_xlfn.XLOOKUP(A9,'Counterparty Trades'!A:A,'Counterparty Trades'!F:F,"Not Found") -> 500 | D9: =_xlfn.XLOOKUP(A9,'Trade Register'!A:A,'Trade Register'!G:G,"Not Found") -> 3020 | E9: =_xlfn.XLOOKUP(A9,'Counterparty Trades'!A:A,'Counterparty Trades'!G:G,"Not Found") -> 3020 | F9: =IF(B9=C9,"Match","Break") -> Match | G9: =IF(D9=E9,"Match","Break") -> Match | H9: =_xlfn.XLOOKUP(A9,'Trade Register'!A:A,'Trade Register'!H:H,"Not Found") -> 46268 | I9: =_xlfn.XLOOKUP(A9,'Counterparty Trades'!A:A,'Counterparty Trades'!H:H,"Not Found") -> 46269 | J9: =IF(H9=I9,"Match","Break") -> Break | K9: =_xlfn.XLOOKUP(A9,'Trade Register'!A:A,'Trade Register'!I:I,"Not Found") -> 46272 | L9: =_xlfn.XLOOKUP(A9,'Counterparty Trades'!A:A,'Counterparty Trades'!I:I,"Not Found") -> 46272 | M9: =IF(K9=L9,"Match","Break") -> Match | N9: =_xlfn.XLOOKUP(A9,'Trade Register'!A:A,'Trade Register'!E:E,"Not Found") -> Sell | O9: =_xlfn.XLOOKUP(A9,'Counterparty Trades'!A:A,'Counterparty Trades'!E:E,"Not Found") -> Sell | P9: =IF(N9=O9,"Match","Break") -> Match
A10: TR009 | B10: =_xlfn.XLOOKUP(A10,'Trade Register'!A:A,'Trade Register'!F:F,"Not Found") -> 700 | C10: =_xlfn.XLOOKUP(A10,'Counterparty Trades'!A:A,'Counterparty Trades'!F:F,"Not Found") -> 700 | D10: =_xlfn.XLOOKUP(A10,'Trade Register'!A:A,'Trade Register'!G:G,"Not Found") -> 1980 | E10: =_xlfn.XLOOKUP(A10,'Counterparty Trades'!A:A,'Counterparty Trades'!G:G,"Not Found") -> 1980 | F10: =IF(B10=C10,"Match","Break") -> Match | G10: =IF(D10=E10,"Match","Break") -> Match | H10: =_xlfn.XLOOKUP(A10,'Trade Register'!A:A,'Trade Register'!H:H,"Not Found") -> 46268 | I10: =_xlfn.XLOOKUP(A10,'Counterparty Trades'!A:A,'Counterparty Trades'!H:H,"Not Found") -> 46268 | J10: =IF(H10=I10,"Match","Break") -> Match | K10: =_xlfn.XLOOKUP(A10,'Trade Register'!A:A,'Trade Register'!I:I,"Not Found") -> 46272 | L10: =_xlfn.XLOOKUP(A10,'Counterparty Trades'!A:A,'Counterparty Trades'!I:I,"Not Found") -> 46273 | M10: =IF(K10=L10,"Match","Break") -> Break | N10: =_xlfn.XLOOKUP(A10,'Trade Register'!A:A,'Trade Register'!E:E,"Not Found") -> Buy | O10: =_xlfn.XLOOKUP(A10,'Counterparty Trades'!A:A,'Counterparty Trades'!E:E,"Not Found") -> Buy | P10: =IF(N10=O10,"Match","Break") -> Match
A11: TR010 | B11: =_xlfn.XLOOKUP(A11,'Trade Register'!A:A,'Trade Register'!F:F,"Not Found") -> 900 | C11: =_xlfn.XLOOKUP(A11,'Counterparty Trades'!A:A,'Counterparty Trades'!F:F,"Not Found") -> 900 | D11: =_xlfn.XLOOKUP(A11,'Trade Register'!A:A,'Trade Register'!G:G,"Not Found") -> 1520 | E11: =_xlfn.XLOOKUP(A11,'Counterparty Trades'!A:A,'Counterparty Trades'!G:G,"Not Found") -> 1520 | F11: =IF(B11=C11,"Match","Break") -> Match | G11: =IF(D11=E11,"Match","Break") -> Match | H11: =_xlfn.XLOOKUP(A11,'Trade Register'!A:A,'Trade Register'!H:H,"Not Found") -> 46269 | I11: =_xlfn.XLOOKUP(A11,'Counterparty Trades'!A:A,'Counterparty Trades'!H:H,"Not Found") -> 46269 | J11: =IF(H11=I11,"Match","Break") -> Match | K11: =_xlfn.XLOOKUP(A11,'Trade Register'!A:A,'Trade Register'!I:I,"Not Found") -> 46273 | L11: =_xlfn.XLOOKUP(A11,'Counterparty Trades'!A:A,'Counterparty Trades'!I:I,"Not Found") -> 46273 | M11: =IF(K11=L11,"Match","Break") -> Match | N11: =_xlfn.XLOOKUP(A11,'Trade Register'!A:A,'Trade Register'!E:E,"Not Found") -> Sell | O11: =_xlfn.XLOOKUP(A11,'Counterparty Trades'!A:A,'Counterparty Trades'!E:E,"Not Found") -> Buy | P11: =IF(N11=O11,"Match","Break") -> Break
A12: TR011 | B12: =_xlfn.XLOOKUP(A12,'Trade Register'!A:A,'Trade Register'!F:F,"Not Found") -> 100 | C12: =_xlfn.XLOOKUP(A12,'Counterparty Trades'!A:A,'Counterparty Trades'!F:F,"Not Found") -> 100 | D12: =_xlfn.XLOOKUP(A12,'Trade Register'!A:A,'Trade Register'!G:G,"Not Found") -> 98.5 | E12: =_xlfn.XLOOKUP(A12,'Counterparty Trades'!A:A,'Counterparty Trades'!G:G,"Not Found") -> 98.5 | F12: =IF(B12=C12,"Match","Break") -> Match | G12: =IF(D12=E12,"Match","Break") -> Match | H12: =_xlfn.XLOOKUP(A12,'Trade Register'!A:A,'Trade Register'!H:H,"Not Found") -> 46269 | I12: =_xlfn.XLOOKUP(A12,'Counterparty Trades'!A:A,'Counterparty Trades'!H:H,"Not Found") -> 46269 | J12: =IF(H12=I12,"Match","Break") -> Match | K12: =_xlfn.XLOOKUP(A12,'Trade Register'!A:A,'Trade Register'!I:I,"Not Found") -> 46273 | L12: =_xlfn.XLOOKUP(A12,'Counterparty Trades'!A:A,'Counterparty Trades'!I:I,"Not Found") -> 46273 | M12: =IF(K12=L12,"Match","Break") -> Match | N12: =_xlfn.XLOOKUP(A12,'Trade Register'!A:A,'Trade Register'!E:E,"Not Found") -> Buy | O12: =_xlfn.XLOOKUP(A12,'Counterparty Trades'!A:A,'Counterparty Trades'!E:E,"Not Found") -> Buy | P12: =IF(N12=O12,"Match","Break") -> Match
A13: TR012 | B13: =_xlfn.XLOOKUP(A13,'Trade Register'!A:A,'Trade Register'!F:F,"Not Found") -> 150 | C13: =_xlfn.XLOOKUP(A13,'Counterparty Trades'!A:A,'Counterparty Trades'!F:F,"Not Found") -> 150 | D13: =_xlfn.XLOOKUP(A13,'Trade Register'!A:A,'Trade Register'!G:G,"Not Found") -> 101.25 | E13: =_xlfn.XLOOKUP(A13,'Counterparty Trades'!A:A,'Counterparty Trades'!G:G,"Not Found") -> 101.25 | F13: =IF(B13=C13,"Match","Break") -> Match | G13: =IF(D13=E13,"Match","Break") -> Match | H13: =_xlfn.XLOOKUP(A13,'Trade Register'!A:A,'Trade Register'!H:H,"Not Found") -> 46269 | I13: =_xlfn.XLOOKUP(A13,'Counterparty Trades'!A:A,'Counterparty Trades'!H:H,"Not Found") -> 46269 | J13: =IF(H13=I13,"Match","Break") -> Match | K13: =_xlfn.XLOOKUP(A13,'Trade Register'!A:A,'Trade Register'!I:I,"Not Found") -> 46273 | L13: =_xlfn.XLOOKUP(A13,'Counterparty Trades'!A:A,'Counterparty Trades'!I:I,"Not Found") -> 46273 | M13: =IF(K13=L13,"Match","Break") -> Match | N13: =_xlfn.XLOOKUP(A13,'Trade Register'!A:A,'Trade Register'!E:E,"Not Found") -> Sell | O13: =_xlfn.XLOOKUP(A13,'Counterparty Trades'!A:A,'Counterparty Trades'!E:E,"Not Found") -> Sell | P13: =IF(N13=O13,"Match","Break") -> Match
... A21: TR020 | B21: =_xlfn.XLOOKUP(A21,'Trade Register'!A:A,'Trade Register'!F:F,"Not Found") -> 400 | C21: =_xlfn.XLOOKUP(A21,'Counterparty Trades'!A:A,'Counterparty Trades'!F:F,"Not Found") -> 400 | D21: =_xlfn.XLOOKUP(A21,'Trade Register'!A:A,'Trade Register'!G:G,"Not Found") -> 2450 | E21: =_xlfn.XLOOKUP(A21,'Counterparty Trades'!A:A,'Counterparty Trades'!G:G,"Not Found") -> 2450 | F21: =IF(B21=C21,"Match","Break") -> Match | G21: =IF(D21=E21,"Match","Break") -> Match | H21: =_xlfn.XLOOKUP(A21,'Trade Register'!A:A,'Trade Register'!H:H,"Not Found") -> 46271 | I21: =_xlfn.XLOOKUP(A21,'Counterparty Trades'!A:A,'Counterparty Trades'!H:H,"Not Found") -> 46271 | J21: =IF(H21=I21,"Match","Break") -> Match | K21: =_xlfn.XLOOKUP(A21,'Trade Register'!A:A,'Trade Register'!I:I,"Not Found") -> 46273 | L21: =_xlfn.XLOOKUP(A21,'Counterparty Trades'!A:A,'Counterparty Trades'!I:I,"Not Found") -> 46273 | M21: =IF(K21=L21,"Match","Break") -> Match | N21: =_xlfn.XLOOKUP(A21,'Trade Register'!A:A,'Trade Register'!E:E,"Not Found") -> Sell | O21: =_xlfn.XLOOKUP(A21,'Counterparty Trades'!A:A,'Counterparty Trades'!E:E,"Not Found") -> Sell | P21: =IF(N21=O21,"Match","Break") -> Match

Sheet Exception Report
A1: Trade ID | B1: Break Type | C1: Internal Value | D1: Counterparty Value | E1: Status
A2: TR005 | B2: Price | C2: 210 | D2: 211 | E2: Break
A3: TR006 | B3: Quantity | C3: 600 | D3: 650 | E3: Break
A4: TR008 | B4: Trade Date | C4: 46268 | D4: 46269 | E4: Break
A5: TR009 | B5: Settlement Date | C5: 46272 | D5: 46273 | E5: Break
A6: TR010 | B6: Buy/Sell | C6: Sell | D6: Buy | E6: Break
A8: Total Trade Breaks | B8: =COUNTIF(E2:E6,"Break") -> 5

Sheet Dashboard
A1: Investment Banking Trade Reconciliation Dashboard
A3: Metric | B3: Value
A4: Total Trades | B4: =COUNTA('Trade Matching'!A2:A21) -> 20
A5: Matched Trades | B5: =COUNTIFS('Trade Matching'!F2:F21,"Match",'Trade Matching'!G2:G21,"Match",'Trade Matching'!J2:J21,"Match",'Trade Matching'!M2:M21,"Match",'Trade Matching'!P2:P21,"Match") -> 15
A6: Trade Breaks | B6: =B4-B5 -> 5
A8: Match Rate | B8: =B5/B4 -> 0.75
A10: Asset Type | B10: Trade Count
A11: Equity | B11: =COUNTIF('Trade Register'!D:D,A11) -> 14
A12: Bond | B12: =COUNTIF('Trade Register'!D:D,A12) -> 2
A13: FX | B13: =COUNTIF('Trade Register'!D:D,A13) -> 2
A14: Future | B14: =COUNTIF('Trade Register'!D:D,A14) -> 2
A17: Break Type | B17: Count
A18: Quantity Break | B18: =COUNTIF('Trade Matching'!F2:F21,"Break") -> 1
A19: Price Break | B19: =COUNTIF('Trade Matching'!G2:G21,"Break") -> 1
A20: Trade Date Break | B20: =COUNTIF('Trade Matching'!J2:J21,"Break") -> 1
A21: Settlement Date Break | B21: =COUNTIF('Trade Matching'!M2:M21,"Break") -> 1
A22: Buy/Sell Break | B22: =COUNTIF('Trade Matching'!P2:P21,"Break") -> 1
